dbt/adapters/fivetran/__init__.py
dbt/adapters/fivetran/__version__.py
dbt/adapters/fivetran/adapter.py
dbt/adapters/fivetran/connections.py
dbt/adapters/fivetran/credentials.py
dbt/include/fivetran/__init__.py
dbt/include/fivetran/dbt_project.yml
dbt/include/fivetran/sample_profiles.yml
dbt/include/fivetran/macros/adapters.sql
dbt/include/fivetran/macros/utils/any_value.sql
dbt/include/fivetran/macros/utils/date.sql
dbt/include/fivetran/macros/utils/listagg.sql
dbt/include/fivetran/macros/utils/relations.sql
dbt/include/fivetran/macros/utils/splitpart.sql
dbt/include/fivetran/macros/utils/timestamp.sql
dbt_fivetran-0.0.33.dist-info/licenses/LICENSE.md
dbt_fivetran-0.0.33.dist-info/METADATA
dbt_fivetran-0.0.33.dist-info/WHEEL
dbt_fivetran-0.0.33.dist-info/top_level.txt
dbt_fivetran-0.0.33.dist-info/RECORD
