Metadata-Version: 2.4
Name: dbt-fivetran
Version: 0.0.33
Summary: dbt (data build tool) adapter for Fivetran Datalake
Home-page: https://github.com/fivetran/dbt-fivetran
Author: Emrah Diril
Author-email: support@fivetran.com
Classifier: License :: OSI Approved :: Apache Software License
Classifier: Operating System :: Microsoft :: Windows
Classifier: Operating System :: MacOS :: MacOS X
Classifier: Operating System :: POSIX :: Linux
Classifier: Programming Language :: Python :: 3.9
Classifier: Programming Language :: Python :: 3.10
Classifier: Programming Language :: Python :: 3.11
Classifier: Programming Language :: Python :: 3.12
Requires-Python: >=3.9
License-File: LICENSE.md
Requires-Dist: dbt-common<2.0,>=1.10
Requires-Dist: dbt-adapters<2.0,>=1.7
Requires-Dist: dbt-duckdb>=1.8.3
Requires-Dist: pyarrow>=18.0.0
Requires-Dist: pyiceberg>=0.8.1
Requires-Dist: dbt-core>=1.8.0
Dynamic: author
Dynamic: author-email
Dynamic: classifier
Dynamic: description
Dynamic: description-content-type
Dynamic: home-page
Dynamic: license-file
Dynamic: requires-dist
Dynamic: requires-python
Dynamic: summary
